strip_docs/__init__.py
strip_docs/run.py
strip_docs/strip_docs.py
strip_docs-1.0.dist-info/LICENSE
strip_docs-1.0.dist-info/METADATA
strip_docs-1.0.dist-info/WHEEL
strip_docs-1.0.dist-info/entry_points.txt
strip_docs-1.0.dist-info/top_level.txt
strip_docs-1.0.dist-info/RECORD
