Metadata-Version: 2.1
Name: strip-docs
Version: 1.0
Summary: A utility to remove all docstrings from your project
Home-page: https://github.com/smok-serwis/strip-docs
Author: Ned Batchelder
License: UNKNOWN
Project-URL: Code, https://github.com/smok-serwis/strip-docs
Project-URL: Issue tracker, https://github.com/smok-serwis/strip-docs/issues
Keywords: docs,stripping,pydoc,removal
Platform: UNKNOWN
Classifier: Programming Language :: Python
Classifier: Programming Language :: Python :: 2.7
Classifier: Programming Language :: Python :: 3.3
Classifier: Programming Language :: Python :: 3.4
Classifier: Programming Language :: Python :: 3.5
Classifier: Programming Language :: Python :: 3.6
Classifier: Programming Language :: Python :: 3.7
Classifier: Programming Language :: Python :: 3.8
Classifier: Programming Language :: Python :: 3.9
Classifier: Programming Language :: Python :: Implementation :: CPython
Classifier: Operating System :: POSIX
Classifier: Operating System :: OS Independent
Classifier: Development Status :: 5 - Production/Stable
Classifier: License :: OSI Approved :: MIT License
Classifier: Topic :: System :: Software Distribution
